py_logging_context/__init__.py
py_logging_context-0.1.1.dist-info/LICENSE
py_logging_context-0.1.1.dist-info/METADATA
py_logging_context-0.1.1.dist-info/WHEEL
py_logging_context-0.1.1.dist-info/top_level.txt
py_logging_context-0.1.1.dist-info/RECORD
