Metadata-Version: 2.1
Name: py-logging-context
Version: 0.1.1
Summary: A Python util for automatically adding extra log fields to logs
Author-email: Dean Gurvitz <deansg@gmail.com>
License: Apache License
Project-URL: Homepage, https://github.com/deansg/py-logging-context
Classifier: License :: OSI Approved :: Apache Software License
Classifier: Programming Language :: Python
Classifier: Programming Language :: Python :: 3
Requires-Python: >=3.7
License-File: LICENSE
Provides-Extra: dev
